TOPSIS-Harshita-101803259/__init__.py
TOPSIS_Harshita_101803259/__init__.py
TOPSIS_Harshita_101803259-0.0.2.dist-info/LICENCE.txt
TOPSIS_Harshita_101803259-0.0.2.dist-info/METADATA
TOPSIS_Harshita_101803259-0.0.2.dist-info/WHEEL
TOPSIS_Harshita_101803259-0.0.2.dist-info/entry_points.txt
TOPSIS_Harshita_101803259-0.0.2.dist-info/top_level.txt
TOPSIS_Harshita_101803259-0.0.2.dist-info/RECORD
