Metadata-Version: 2.1
Name: TOPSIS-Harshita-101803259
Version: 0.0.2
Summary: implementation of topsis
Home-page: UNKNOWN
Author: harshita
Author-email: UNKNOWN
License: MIT
Platform: UNKNOWN
Requires-Dist: pandas
